graphanime/__init__.py
graphanime/algorithm.py
graphanime/animation.py
graphanime/graph.py
graphanime-0.1.1.dist-info/METADATA
graphanime-0.1.1.dist-info/WHEEL
graphanime-0.1.1.dist-info/top_level.txt
graphanime-0.1.1.dist-info/RECORD
