Metadata-Version: 2.1
Name: graphanime
Version: 0.1.1
Summary: create execution graph in GIF/PDF with LaTex
Home-page: https://github.com/Sosso8305/LaTeX-to-GIF-Python
Author: ALTAVILLA Théo / DUPLAN Xavier / EL RAWAS Gaëthan / ZOUAOUI Sofiane
Author-email: sofiane.zouaoui@insa-cvl.fr
License: MIT Lisence
Platform: UNKNOWN
Classifier: Programming Language :: Python
Classifier: Natural Language :: French
Requires-Dist: pdf2image
Requires-Dist: apng
